orgtbl/__init__.py
orgtbl/__main__.py
orgtbl/xlsx/__init__.py
orgtbl/xlsx/__main__.py
orgtbl/xlsx/looper/__init__.py
orgtbl/xlsx/looper/__main__.py
orgtbl/xlsx2json/__init__.py
orgtbl/xlsx2json/__main__.py
orgtbl-0.9.1.dist-info/LICENSE
orgtbl-0.9.1.dist-info/METADATA
orgtbl-0.9.1.dist-info/WHEEL
orgtbl-0.9.1.dist-info/top_level.txt
orgtbl-0.9.1.dist-info/RECORD
