Metadata-Version: 2.1
Name: orgtbl
Version: 0.9.1
Summary: Quickly convert emacs org-mode tables to Excel
Author-email: Robert Degen <turbodev@mailbox.org>
Project-URL: Homepage, https://github.com/turbo-bert
Project-URL: Issues, https://github.com/turbo-bert
Classifier: Programming Language :: Python :: 3
Classifier: License :: OSI Approved :: MIT License
Classifier: Operating System :: OS Independent
Requires-Python: >=3.8
License-File: LICENSE
Requires-Dist: pandas
Requires-Dist: openpyxl
